metool/__init__.py
metool/notebook.py
metool/notebook_deploy.py
metool/templates/__init__.py
metool/templates/notebook.md
metool-0.1.10.dist-info/entry_points.txt
metool-0.1.10.dist-info/WHEEL
metool-0.1.10.dist-info/METADATA
metool-0.1.10.dist-info/RECORD
